ptt-0.3.dist-info/zip-safe
ptt-0.3.dist-info/RECORD
ptt-0.3.dist-info/WHEEL
ptt-0.3.dist-info/METADATA
ptt-0.3.dist-info/DESCRIPTION.rst
ptt-0.3.dist-info/top_level.txt
ptt-0.3.dist-info/metadata.json
ptt-0.3.data/scripts/ptt
ptt-0.3.data/data/share/icons/hicolor/scalable/apps/ptt/icon.svg
ptt-0.3.data/data/share/applications/ptt.desktop/ptt.desktop
pttlib/PttEditor.py
pttlib/HelpAbout.py
pttlib/Share.py
pttlib/SubfolderList.py
pttlib/IPFSDag.py
pttlib/TrackList.py
pttlib/__init__.py
pttlib/NewSubfolderEdit.py
pttlib/paths.py
pttlib/data/VERSION
pttlib/data/help_about.ui
pttlib/data/share.ui
pttlib/data/icon.svg
pttlib/data/story.html
pttlib/data/main.ui
