Metadata-Version: 2.0
Name: ptt
Version: 0.3
Summary: ptt - a program for recording, editing, and sharing audio essays.
Home-page: UNKNOWN
Author: Timothy Hobbs
Author-email: timothy@hobbs.cz
License: AGPL-3.0
Keywords: audio
Platform: UNKNOWN
Classifier: Development Status :: 3 - Alpha
Classifier: License :: OSI Approved :: GNU Affero General Public License v3 or later (AGPLv3+)
Classifier: Programming Language :: Python :: 3.0
Requires-Dist: requests
